mcp_server_bigquery/__init__.py
mcp_server_bigquery/__main__.py
mcp_server_bigquery/custom_server.py
mcp_server_bigquery/database.py
mcp_server_bigquery/models.py
mcp_server_bigquery/server.py
mseep_mcp_server_bigquery-0.3.5.dist-info/licenses/LICENSE
mseep_mcp_server_bigquery-0.3.5.dist-info/METADATA
mseep_mcp_server_bigquery-0.3.5.dist-info/WHEEL
mseep_mcp_server_bigquery-0.3.5.dist-info/entry_points.txt
mseep_mcp_server_bigquery-0.3.5.dist-info/top_level.txt
mseep_mcp_server_bigquery-0.3.5.dist-info/RECORD
